Workbook

Sheet Présentation
B2: BUSINESS PLAN — SCI L&A
B3: Investissement immobilier locatif — Zone frontalière luxembourgeoise
B6: Associés | C6: Lucas Lamquet & Adrien Fleuriot
B7: Structure juridique | C7: SCI à l'IS (Société Civile Immobilière)
B8: Répartition des parts | C8: 50 % Lucas Lamquet / 50 % Adrien Fleuriot
B9: Statut SCI | C9: À constituer
B10: Zone d'investissement | C10: Rayon 60 km — Frontière luxembourgeoise (54 / 57 / 55)
B11: Bien ciblé | C11: Maison ou immeuble ≥ 100 m² — Division en 2 lots T2
B12: Stratégie | C12: Revenus locatifs + plus-value à la revente
B13: Date du document | C13: 11 mars 2026
B15: DESCRIPTION DU PROJET
B16: La SCI L&A a pour objet l'acquisition d'un bien immobilier situé dans le rayon 60 km
B17: de la frontière luxembourgeoise (Meurthe-et-Moselle 54, Moselle 57, Meuse 55).
B19: Le bien ciblé est une maison ou un immeuble d'une surface minimale de 100 m², à
B20: rénover, sans copropriété existante, avec parking. L'objectif est de le diviser en
B21: 2 appartements T2 de ~50 m² chacun destinés à la location.
B23: La zone frontalière bénéficie d'une demande locative structurelle forte, portée par
B24: les +60 000 emplois attendus au Luxembourg d'ici 2030 et l'afflux de travailleurs
B25: frontaliers cherchant à se loger côté français à des loyers bien inférieurs.
B27: 🟡 Les cellules surlignées en jaune dans l'onglet "Paramètres" sont librement modifiables. Tous les calculs (synthèse, prévisionnel, amortissement, revente) se mettent à jour automatiquement.

Sheet Paramètres
A1: PARAMÈTRES DU PROJET — SCI L&A
A2: 🟡 Cellules jaunes = saisie libre | ⬜ Cellules grises = calculées automatiquement
A4: ACQUISITION
A5: Prix d'achat estimé | B5: 165000 | C5: €
A6: Frais de notaire | B6: 0.08 | C6: %
A7: Montant frais de notaire | B7: =ROUND(B5*B6,0) | C7: € — calculé
A8: Budget travaux | C8: € — à compléter (laisser vide si inconnu)
A9: Frais de dossier / garantie | B9: 3000 | C9: €
A10: TOTAL INVESTISSEMENT | B10: =B5+IFERROR(B8,0)+B7+B9
A12: FINANCEMENT
A13: Apport personnel | B13: 0 | C13: € (0 = financement total)
A14: Montant à emprunter | B14: =B10-B13 | C14: € — calculé
A15: Taux d'intérêt annuel | B15: 0.035 | C15: %
A16: Durée du prêt | B16: 20 | C16: ans
A17: Mensualité estimée | B17: =IFERROR(PMT(B15/12,B16*12,-B14),0) | C17: €/mois — calculé
A18: Coût total du crédit | B18: =IFERROR(B17*B16*12-B14,0) | C18: € — calculé
A20: REVENUS LOCATIFS
A21: Loyer mensuel — Lot 1 (T2 ~50 m²) | B21: 550 | C21: €/mois
A22: Loyer mensuel — Lot 2 (T2 ~50 m²) | B22: 550 | C22: €/mois
A23: Taux d'occupation annuel | B23: 0.92 | C23: %
A24: Revenu brut mensuel (net occupation) | B24: =(B21+B22)*B23 | C24: €/mois — calculé
A25: Revenu brut annuel | B25: =ROUND(B24*12,0) | C25: €/an — calculé
A27: CHARGES ANNUELLES ESTIMÉES
A28: Taxe foncière | B28: 1200 | C28: €/an
A29: Assurance PNO (2 lots) | B29: 600 | C29: €/an
A30: Entretien / provisions | B30: 800 | C30: €/an
A31: Comptabilité SCI | B31: 600 | C31: €/an
A32: TOTAL CHARGES ANNUELLES | B32: =SUM(B28:B31)
A34: HYPOTHÈSES & FISCALITÉ — SCI À L'IS
A35: Revalorisation des loyers / an | B35: 0.015 | C35: %
A36: Plus-value immobilière estimée / an | B36: 0.02 | C36: %
A37: Durée d'amortissement comptable du bien | B37: 30 | C37: ans
A38: Taux IS réduit (PME) | B38: 0.15 | C38: %
A39: Plafond bénéfice IS réduit | B39: 42500 | C39: €
A40: Taux IS normal | B40: 0.25 | C40: %
A41: Flat tax dividendes (PFU) | B41: 0.3 | C41: %
A42: Amortissement comptable annuel | B42: =IFERROR((B5*0.8+IFERROR(B8,0))/B37,0) | C42: €/an — calculé (terrain = 20% non amortissable)
A44: ℹ️ SCI à l'IS : le terrain (~20% du prix d'achat) n'est pas amortissable. Les travaux sont amortis sur la même durée que le bien. Ces paramètres fiscaux doivent être validés par un expert-comptable.

Sheet Synthèse
A1: SYNTHÈSE FINANCIÈRE — SCI L&A
A3: Budget total investissement | D3: Montant à emprunter
A4: =Paramètres!B10 | D4: =Paramètres!B14
A6: Apport personnel | D6: Mensualité emprunt
A7: =Paramètres!B13 | D7: =Paramètres!B17
A9: Revenus locatifs bruts / an | D9: Charges exploitation / an
A10: =Paramètres!B25 | D10: =Paramètres!B32
A12: Excédent brut d'exploitation / an | D12: Cashflow net mensuel (avant IS)
A13: =Paramètres!B25-Paramètres!B32 | D13: =(Paramètres!B25-Paramètres!B32)/12-Paramètres!B17
A15: Rendement brut | D15: Rendement net (après charges)
A16: =Paramètres!B25/Paramètres!B10 | D16: =(Paramètres!B25-Paramètres!B32)/Paramètres!B10
A18: RÉCAPITULATIF DU PLAN DE FINANCEMENT
A19: Prix d'achat | E19: =Paramètres!B5
A20: Frais de notaire (8%) | E20: =Paramètres!B7
A21: Budget travaux | E21: =IFERROR(Paramètres!B8,0)
A22: Frais de dossier / garantie | E22: =Paramètres!B9
A23: TOTAL COÛT DU PROJET | E23: =Paramètres!B10
A24: dont Apport | E24: =Paramètres!B13
A25: dont Emprunt bancaire | E25: =Paramètres!B14
A26: Taux d'intérêt et durée modifiables dans l'onglet Paramètres (cellules jaunes)
A27: Mensualité | E27: =Paramètres!B17
A28: Coût total du crédit | E28: =Paramètres!B18
A30: ⚠️ Le budget travaux est intentionnellement laissé vide — à compléter après estimation. Tous les calculs s'adaptent automatiquement.

Sheet Prévisionnel 20 ans
A1: PRÉVISIONNEL D'EXPLOITATION — 20 ANS — SCI L&A (IS)
A2: SCI à l'IS — Amortissement comptable & intérêts déduits du résultat imposable | Résultats indicatifs — à valider avec un expert-comptable
A4: Année | B4: Revenus locatifs (€) | C4: Charges exploit. (€) | D4: EBE (€) | E4: Intérêts emprunt (€) | F4: Amort. comptable (€) | G4: Résultat fiscal (€) | H4: IS dû (€) | I4: Résultat net IS (€) | J4: Annuité emprunt (€) | K4: Cashflow net (€) | L4: Capital restant dû (€) | M4: Valeur estimée (€) | N4: Patrimoine net (€)
A5: 2026 | B5: =Paramètres!B25 | C5: =Paramètres!B32 | D5: =B5-C5 | E5: =IFERROR(-CUMIPMT(Paramètres!B15/12,Paramètres!B16*12,Paramètres!B14,1,12,0),0) | F5: =Paramètres!B42 | G5: =D5-E5-F5 | H5: =IF(G5>0,MIN(G5,Paramètres!B39)*Paramètres!B38+MAX(0,G5-Paramètres!B39)*Paramètres!B40,0) | I5: =G5-H5 | J5: =Paramètres!B17*12 | K5: =D5-H5-J5 | L5: =IFERROR(Paramètres!B14+CUMPRINC(Paramètres!B15/12,Paramètres!B16*12,Paramètres!B14,1,12,0),0) | M5: =ROUND((Paramètres!B5+IFERROR(Paramètres!B8,0))*(1+Paramètres!B36),0) | N5: =M5-L5
A6: 2027 | B6: =ROUND(B5*(1+Paramètres!B35),0) | C6: =Paramètres!B32 | D6: =B6-C6 | E6: =IFERROR(-CUMIPMT(Paramètres!B15/12,Paramètres!B16*12,Paramètres!B14,13,24,0),0) | F6: =Paramètres!B42 | G6: =D6-E6-F6 | H6: =IF(G6>0,MIN(G6,Paramètres!B39)*Paramètres!B38+MAX(0,G6-Paramètres!B39)*Paramètres!B40,0) | I6: =G6-H6 | J6: =Paramètres!B17*12 | K6: =D6-H6-J6 | L6: =IFERROR(Paramètres!B14+CUMPRINC(Paramètres!B15/12,Paramètres!B16*12,Paramètres!B14,1,24,0),0) | M6: =ROUND(M5*(1+Paramètres!B36),0) | N6: =M6-L6
A7: 2028 | B7: =ROUND(B6*(1+Paramètres!B35),0) | C7: =Paramètres!B32 | D7: =B7-C7 | E7: =IFERROR(-CUMIPMT(Paramètres!B15/12,Paramètres!B16*12,Paramètres!B14,25,36,0),0) | F7: =Paramètres!B42 | G7: =D7-E7-F7 | H7: =IF(G7>0,MIN(G7,Paramètres!B39)*Paramètres!B38+MAX(0,G7-Paramètres!B39)*Paramètres!B40,0) | I7: =G7-H7 | J7: =Paramètres!B17*12 | K7: =D7-H7-J7 | L7: =IFERROR(Paramètres!B14+CUMPRINC(Paramètres!B15/12,Paramètres!B16*12,Paramètres!B14,1,36,0),0) | M7: =ROUND(M6*(1+Paramètres!B36),0) | N7: =M7-L7
A8: 2029 | B8: =ROUND(B7*(1+Paramètres!B35),0) | C8: =Paramètres!B32 | D8: =B8-C8 | E8: =IFERROR(-CUMIPMT(Paramètres!B15/12,Paramètres!B16*12,Paramètres!B14,37,48,0),0) | F8: =Paramètres!B42 | G8: =D8-E8-F8 | H8: =IF(G8>0,MIN(G8,Paramètres!B39)*Paramètres!B38+MAX(0,G8-Paramètres!B39)*Paramètres!B40,0) | I8: =G8-H8 | J8: =Paramètres!B17*12 | K8: =D8-H8-J8 | L8: =IFERROR(Paramètres!B14+CUMPRINC(Paramètres!B15/12,Paramètres!B16*12,Paramètres!B14,1,48,0),0) | M8: =ROUND(M7*(1+Paramètres!B36),0) | N8: =M8-L8
A9: 2030 | B9: =ROUND(B8*(1+Paramètres!B35),0) | C9: =Paramètres!B32 | D9: =B9-C9 | E9: =IFERROR(-CUMIPMT(Paramètres!B15/12,Paramètres!B16*12,Paramètres!B14,49,60,0),0) | F9: =Paramètres!B42 | G9: =D9-E9-F9 | H9: =IF(G9>0,MIN(G9,Paramètres!B39)*Paramètres!B38+MAX(0,G9-Paramètres!B39)*Paramètres!B40,0) | I9: =G9-H9 | J9: =Paramètres!B17*12 | K9: =D9-H9-J9 | L9: =IFERROR(Paramètres!B14+CUMPRINC(Paramètres!B15/12,Paramètres!B16*12,Paramètres!B14,1,60,0),0) | M9: =ROUND(M8*(1+Paramètres!B36),0) | N9: =M9-L9
A10: 2031 | B10: =ROUND(B9*(1+Paramètres!B35),0) | C10: =Paramètres!B32 | D10: =B10-C10 | E10: =IFERROR(-CUMIPMT(Paramètres!B15/12,Paramètres!B16*12,Paramètres!B14,61,72,0),0) | F10: =Paramètres!B42 | G10: =D10-E10-F10 | H10: =IF(G10>0,MIN(G10,Paramètres!B39)*Paramètres!B38+MAX(0,G10-Paramètres!B39)*Paramètres!B40,0) | I10: =G10-H10 | J10: =Paramètres!B17*12 | K10: =D10-H10-J10 | L10: =IFERROR(Paramètres!B14+CUMPRINC(Paramètres!B15/12,Paramètres!B16*12,Paramètres!B14,1,72,0),0) | M10: =ROUND(M9*(1+Paramètres!B36),0) | N10: =M10-L10
A11: 2032 | B11: =ROUND(B10*(1+Paramètres!B35),0) | C11: =Paramètres!B32 | D11: =B11-C11 | E11: =IFERROR(-CUMIPMT(Paramètres!B15/12,Paramètres!B16*12,Paramètres!B14,73,84,0),0) | F11: =Paramètres!B42 | G11: =D11-E11-F11 | H11: =IF(G11>0,MIN(G11,Paramètres!B39)*Paramètres!B38+MAX(0,G11-Paramètres!B39)*Paramètres!B40,0) | I11: =G11-H11 | J11: =Paramètres!B17*12 | K11: =D11-H11-J11 | L11: =IFERROR(Paramètres!B14+CUMPRINC(Paramètres!B15/12,Paramètres!B16*12,Paramètres!B14,1,84,0),0) | M11: =ROUND(M10*(1+Paramètres!B36),0) | N11: =M11-L11
A12: 2033 | B12: =ROUND(B11*(1+Paramètres!B35),0) | C12: =Paramètres!B32 | D12: =B12-C12 | E12: =IFERROR(-CUMIPMT(Paramètres!B15/12,Paramètres!B16*12,Paramètres!B14,85,96,0),0) | F12: =Paramètres!B42 | G12: =D12-E12-F12 | H12: =IF(G12>0,MIN(G12,Paramètres!B39)*Paramètres!B38+MAX(0,G12-Paramètres!B39)*Paramètres!B40,0) | I12: =G12-H12 | J12: =Paramètres!B17*12 | K12: =D12-H12-J12 | L12: =IFERROR(Paramètres!B14+CUMPRINC(Paramètres!B15/12,Paramètres!B16*12,Paramètres!B14,1,96,0),0) | M12: =ROUND(M11*(1+Paramètres!B36),0) | N12: =M12-L12
A13: 2034 | B13: =ROUND(B12*(1+Paramètres!B35),0) | C13: =Paramètres!B32 | D13: =B13-C13 | E13: =IFERROR(-CUMIPMT(Paramètres!B15/12,Paramètres!B16*12,Paramètres!B14,97,108,0),0) | F13: =Paramètres!B42 | G13: =D13-E13-F13 | H13: =IF(G13>0,MIN(G13,Paramètres!B39)*Paramètres!B38+MAX(0,G13-Paramètres!B39)*Paramètres!B40,0) | I13: =G13-H13 | J13: =Paramètres!B17*12 | K13: =D13-H13-J13 | L13: =IFERROR(Paramètres!B14+CUMPRINC(Paramètres!B15/12,Paramètres!B16*12,Paramètres!B14,1,108,0),0) | M13: =ROUND(M12*(1+Paramètres!B36),0) | N13: =M13-L13
A14: 2035 | B14: =ROUND(B13*(1+Paramètres!B35),0) | C14: =Paramètres!B32 | D14: =B14-C14 | E14: =IFERROR(-CUMIPMT(Paramètres!B15/12,Paramètres!B16*12,Paramètres!B14,109,120,0),0) | F14: =Paramètres!B42 | G14: =D14-E14-F14 | H14: =IF(G14>0,MIN(G14,Paramètres!B39)*Paramètres!B38+MAX(0,G14-Paramètres!B39)*Paramètres!B40,0) | I14: =G14-H14 | J14: =Paramètres!B17*12 | K14: =D14-H14-J14 | L14: =IFERROR(Paramètres!B14+CUMPRINC(Paramètres!B15/12,Paramètres!B16*12,Paramètres!B14,1,120,0),0) | M14: =ROUND(M13*(1+Paramètres!B36),0) | N14: =M14-L14
A15: 2036 | B15: =ROUND(B14*(1+Paramètres!B35),0) | C15: =Paramètres!B32 | D15: =B15-C15 | E15: =IFERROR(-CUMIPMT(Paramètres!B15/12,Paramètres!B16*12,Paramètres!B14,121,132,0),0) | F15: =Paramètres!B42 | G15: =D15-E15-F15 | H15: =IF(G15>0,MIN(G15,Paramètres!B39)*Paramètres!B38+MAX(0,G15-Paramètres!B39)*Paramètres!B40,0) | I15: =G15-H15 | J15: =Paramètres!B17*12 | K15: =D15-H15-J15 | L15: =IFERROR(Paramètres!B14+CUMPRINC(Paramètres!B15/12,Paramètres!B16*12,Paramètres!B14,1,132,0),0) | M15: =ROUND(M14*(1+Paramètres!B36),0) | N15: =M15-L15
A16: 2037 | B16: =ROUND(B15*(1+Paramètres!B35),0) | C16: =Paramètres!B32 | D16: =B16-C16 | E16: =IFERROR(-CUMIPMT(Paramètres!B15/12,Paramètres!B16*12,Paramètres!B14,133,144,0),0) | F16: =Paramètres!B42 | G16: =D16-E16-F16 | H16: =IF(G16>0,MIN(G16,Paramètres!B39)*Paramètres!B38+MAX(0,G16-Paramètres!B39)*Paramètres!B40,0) | I16: =G16-H16 | J16: =Paramètres!B17*12 | K16: =D16-H16-J16 | L16: =IFERROR(Paramètres!B14+CUMPRINC(Paramètres!B15/12,Paramètres!B16*12,Paramètres!B14,1,144,0),0) | M16: =ROUND(M15*(1+Paramètres!B36),0) | N16: =M16-L16
A17: 2038 | B17: =ROUND(B16*(1+Paramètres!B35),0) | C17: =Paramètres!B32 | D17: =B17-C17 | E17: =IFERROR(-CUMIPMT(Paramètres!B15/12,Paramètres!B16*12,Paramètres!B14,145,156,0),0) | F17: =Paramètres!B42 | G17: =D17-E17-F17 | H17: =IF(G17>0,MIN(G17,Paramètres!B39)*Paramètres!B38+MAX(0,G17-Paramètres!B39)*Paramètres!B40,0) | I17: =G17-H17 | J17: =Paramètres!B17*12 | K17: =D17-H17-J17 | L17: =IFERROR(Paramètres!B14+CUMPRINC(Paramètres!B15/12,Paramètres!B16*12,Paramètres!B14,1,156,0),0) | M17: =ROUND(M16*(1+Paramètres!B36),0) | N17: =M17-L17
A18: 2039 | B18: =ROUND(B17*(1+Paramètres!B35),0) | C18: =Paramètres!B32 | D18: =B18-C18 | E18: =IFERROR(-CUMIPMT(Paramètres!B15/12,Paramètres!B16*12,Paramètres!B14,157,168,0),0) | F18: =Paramètres!B42 | G18: =D18-E18-F18 | H18: =IF(G18>0,MIN(G18,Paramètres!B39)*Paramètres!B38+MAX(0,G18-Paramètres!B39)*Paramètres!B40,0) | I18: =G18-H18 | J18: =Paramètres!B17*12 | K18: =D18-H18-J18 | L18: =IFERROR(Paramètres!B14+CUMPRINC(Paramètres!B15/12,Paramètres!B16*12,Paramètres!B14,1,168,0),0) | M18: =ROUND(M17*(1+Paramètres!B36),0) | N18: =M18-L18
A19: 2040 | B19: =ROUND(B18*(1+Paramètres!B35),0) | C19: =Paramètres!B32 | D19: =B19-C19 | E19: =IFERROR(-CUMIPMT(Paramètres!B15/12,Paramètres!B16*12,Paramètres!B14,169,180,0),0) | F19: =Paramètres!B42 | G19: =D19-E19-F19 | H19: =IF(G19>0,MIN(G19,Paramètres!B39)*Paramètres!B38+MAX(0,G19-Paramètres!B39)*Paramètres!B40,0) | I19: =G19-H19 | J19: =Paramètres!B17*12 | K19: =D19-H19-J19 | L19: =IFERROR(Paramètres!B14+CUMPRINC(Paramètres!B15/12,Paramètres!B16*12,Paramètres!B14,1,180,0),0) | M19: =ROUND(M18*(1+Paramètres!B36),0) | N19: =M19-L19
A20: 2041 | B20: =ROUND(B19*(1+Paramètres!B35),0) | C20: =Paramètres!B32 | D20: =B20-C20 | E20: =IFERROR(-CUMIPMT(Paramètres!B15/12,Paramètres!B16*12,Paramètres!B14,181,192,0),0) | F20: =Paramètres!B42 | G20: =D20-E20-F20 | H20: =IF(G20>0,MIN(G20,Paramètres!B39)*Paramètres!B38+MAX(0,G20-Paramètres!B39)*Paramètres!B40,0) | I20: =G20-H20 | J20: =Paramètres!B17*12 | K20: =D20-H20-J20 | L20: =IFERROR(Paramètres!B14+CUMPRINC(Paramètres!B15/12,Paramètres!B16*12,Paramètres!B14,1,192,0),0) | M20: =ROUND(M19*(1+Paramètres!B36),0) | N20: =M20-L20
A21: 2042 | B21: =ROUND(B20*(1+Paramètres!B35),0) | C21: =Paramètres!B32 | D21: =B21-C21 | E21: =IFERROR(-CUMIPMT(Paramètres!B15/12,Paramètres!B16*12,Paramètres!B14,193,204,0),0) | F21: =Paramètres!B42 | G21: =D21-E21-F21 | H21: =IF(G21>0,MIN(G21,Paramètres!B39)*Paramètres!B38+MAX(0,G21-Paramètres!B39)*Paramètres!B40,0) | I21: =G21-H21 | J21: =Paramètres!B17*12 | K21: =D21-H21-J21 | L21: =IFERROR(Paramètres!B14+CUMPRINC(Paramètres!B15/12,Paramètres!B16*12,Paramètres!B14,1,204,0),0) | M21: =ROUND(M20*(1+Paramètres!B36),0) | N21: =M21-L21
A22: 2043 | B22: =ROUND(B21*(1+Paramètres!B35),0) | C22: =Paramètres!B32 | D22: =B22-C22 | E22: =IFERROR(-CUMIPMT(Paramètres!B15/12,Paramètres!B16*12,Paramètres!B14,205,216,0),0) | F22: =Paramètres!B42 | G22: =D22-E22-F22 | H22: =IF(G22>0,MIN(G22,Paramètres!B39)*Paramètres!B38+MAX(0,G22-Paramètres!B39)*Paramètres!B40,0) | I22: =G22-H22 | J22: =Paramètres!B17*12 | K22: =D22-H22-J22 | L22: =IFERROR(Paramètres!B14+CUMPRINC(Paramètres!B15/12,Paramètres!B16*12,Paramètres!B14,1,216,0),0) | M22: =ROUND(M21*(1+Paramètres!B36),0) | N22: =M22-L22
A23: 2044 | B23: =ROUND(B22*(1+Paramètres!B35),0) | C23: =Paramètres!B32 | D23: =B23-C23 | E23: =IFERROR(-CUMIPMT(Paramètres!B15/12,Paramètres!B16*12,Paramètres!B14,217,228,0),0) | F23: =Paramètres!B42 | G23: =D23-E23-F23 | H23: =IF(G23>0,MIN(G23,Paramètres!B39)*Paramètres!B38+MAX(0,G23-Paramètres!B39)*Paramètres!B40,0) | I23: =G23-H23 | J23: =Paramètres!B17*12 | K23: =D23-H23-J23 | L23: =IFERROR(Paramètres!B14+CUMPRINC(Paramètres!B15/12,Paramètres!B16*12,Paramètres!B14,1,228,0),0) | M23: =ROUND(M22*(1+Paramètres!B36),0) | N23: =M23-L23
A24: 2045 | B24: =ROUND(B23*(1+Paramètres!B35),0) | C24: =Paramètres!B32 | D24: =B24-C24 | E24: =IFERROR(-CUMIPMT(Paramètres!B15/12,Paramètres!B16*12,Paramètres!B14,229,240,0),0) | F24: =Paramètres!B42 | G24: =D24-E24-F24 | H24: =IF(G24>0,MIN(G24,Paramètres!B39)*Paramètres!B38+MAX(0,G24-Paramètres!B39)*Paramètres!B40,0) | I24: =G24-H24 | J24: =Paramètres!B17*12 | K24: =D24-H24-J24 | L24: =IFERROR(Paramètres!B14+CUMPRINC(Paramètres!B15/12,Paramètres!B16*12,Paramètres!B14,1,240,0),0) | M24: =ROUND(M23*(1+Paramètres!B36),0) | N24: =M24-L24
A25: CUMUL 20 ANS | B25: =SUM(B5:B24) | C25: =SUM(C5:C24) | D25: =SUM(D5:D24) | H25: =SUM(H5:H24) | J25: =SUM(J5:J24) | K25: =SUM(K5:K24) | L25: =L24 | M25: =M24 | N25: =N24
A27: EBE = Revenus − Charges | Résultat fiscal = EBE − Intérêts − Amortissement comptable | IS = 15% ≤ 42 500 € puis 25% | Cashflow net = EBE − IS − Annuité

Sheet Amortissement
A1: TABLEAU D'AMORTISSEMENT — RÉSUMÉ ANNUEL SUR 20 ANS
A2: Calculé automatiquement depuis l'onglet Paramètres — Fonctions financières CUMIPMT / CUMPRINC
A4: Année | B4: Capital début (€) | C4: Annuité annuelle (€) | D4: dont Intérêts (€) | E4: dont Capital remb. (€) | F4: Capital restant dû (€) | G4: % Remboursé
A5: 1 | B5: =Paramètres!B14 | C5: =Paramètres!B17*12 | D5: =IFERROR(-CUMIPMT(Paramètres!B15/12,Paramètres!B16*12,Paramètres!B14,1,12,0),0) | E5: =IFERROR(-CUMPRINC(Paramètres!B15/12,Paramètres!B16*12,Paramètres!B14,1,12,0),0) | F5: =B5-E5 | G5: =IFERROR(1-F5/Paramètres!B14,0)
A6: 2 | B6: =F5 | C6: =Paramètres!B17*12 | D6: =IFERROR(-CUMIPMT(Paramètres!B15/12,Paramètres!B16*12,Paramètres!B14,13,24,0),0) | E6: =IFERROR(-CUMPRINC(Paramètres!B15/12,Paramètres!B16*12,Paramètres!B14,13,24,0),0) | F6: =B6-E6 | G6: =IFERROR(1-F6/Paramètres!B14,0)
A7: 3 | B7: =F6 | C7: =Paramètres!B17*12 | D7: =IFERROR(-CUMIPMT(Paramètres!B15/12,Paramètres!B16*12,Paramètres!B14,25,36,0),0) | E7: =IFERROR(-CUMPRINC(Paramètres!B15/12,Paramètres!B16*12,Paramètres!B14,25,36,0),0) | F7: =B7-E7 | G7: =IFERROR(1-F7/Paramètres!B14,0)
A8: 4 | B8: =F7 | C8: =Paramètres!B17*12 | D8: =IFERROR(-CUMIPMT(Paramètres!B15/12,Paramètres!B16*12,Paramètres!B14,37,48,0),0) | E8: =IFERROR(-CUMPRINC(Paramètres!B15/12,Paramètres!B16*12,Paramètres!B14,37,48,0),0) | F8: =B8-E8 | G8: =IFERROR(1-F8/Paramètres!B14,0)
A9: 5 | B9: =F8 | C9: =Paramètres!B17*12 | D9: =IFERROR(-CUMIPMT(Paramètres!B15/12,Paramètres!B16*12,Paramètres!B14,49,60,0),0) | E9: =IFERROR(-CUMPRINC(Paramètres!B15/12,Paramètres!B16*12,Paramètres!B14,49,60,0),0) | F9: =B9-E9 | G9: =IFERROR(1-F9/Paramètres!B14,0)
A10: 6 | B10: =F9 | C10: =Paramètres!B17*12 | D10: =IFERROR(-CUMIPMT(Paramètres!B15/12,Paramètres!B16*12,Paramètres!B14,61,72,0),0) | E10: =IFERROR(-CUMPRINC(Paramètres!B15/12,Paramètres!B16*12,Paramètres!B14,61,72,0),0) | F10: =B10-E10 | G10: =IFERROR(1-F10/Paramètres!B14,0)
A11: 7 | B11: =F10 | C11: =Paramètres!B17*12 | D11: =IFERROR(-CUMIPMT(Paramètres!B15/12,Paramètres!B16*12,Paramètres!B14,73,84,0),0) | E11: =IFERROR(-CUMPRINC(Paramètres!B15/12,Paramètres!B16*12,Paramètres!B14,73,84,0),0) | F11: =B11-E11 | G11: =IFERROR(1-F11/Paramètres!B14,0)
A12: 8 | B12: =F11 | C12: =Paramètres!B17*12 | D12: =IFERROR(-CUMIPMT(Paramètres!B15/12,Paramètres!B16*12,Paramètres!B14,85,96,0),0) | E12: =IFERROR(-CUMPRINC(Paramètres!B15/12,Paramètres!B16*12,Paramètres!B14,85,96,0),0) | F12: =B12-E12 | G12: =IFERROR(1-F12/Paramètres!B14,0)
A13: 9 | B13: =F12 | C13: =Paramètres!B17*12 | D13: =IFERROR(-CUMIPMT(Paramètres!B15/12,Paramètres!B16*12,Paramètres!B14,97,108,0),0) | E13: =IFERROR(-CUMPRINC(Paramètres!B15/12,Paramètres!B16*12,Paramètres!B14,97,108,0),0) | F13: =B13-E13 | G13: =IFERROR(1-F13/Paramètres!B14,0)
A14: 10 | B14: =F13 | C14: =Paramètres!B17*12 | D14: =IFERROR(-CUMIPMT(Paramètres!B15/12,Paramètres!B16*12,Paramètres!B14,109,120,0),0) | E14: =IFERROR(-CUMPRINC(Paramètres!B15/12,Paramètres!B16*12,Paramètres!B14,109,120,0),0) | F14: =B14-E14 | G14: =IFERROR(1-F14/Paramètres!B14,0)
A15: 11 | B15: =F14 | C15: =Paramètres!B17*12 | D15: =IFERROR(-CUMIPMT(Paramètres!B15/12,Paramètres!B16*12,Paramètres!B14,121,132,0),0) | E15: =IFERROR(-CUMPRINC(Paramètres!B15/12,Paramètres!B16*12,Paramètres!B14,121,132,0),0) | F15: =B15-E15 | G15: =IFERROR(1-F15/Paramètres!B14,0)
A16: 12 | B16: =F15 | C16: =Paramètres!B17*12 | D16: =IFERROR(-CUMIPMT(Paramètres!B15/12,Paramètres!B16*12,Paramètres!B14,133,144,0),0) | E16: =IFERROR(-CUMPRINC(Paramètres!B15/12,Paramètres!B16*12,Paramètres!B14,133,144,0),0) | F16: =B16-E16 | G16: =IFERROR(1-F16/Paramètres!B14,0)
A17: 13 | B17: =F16 | C17: =Paramètres!B17*12 | D17: =IFERROR(-CUMIPMT(Paramètres!B15/12,Paramètres!B16*12,Paramètres!B14,145,156,0),0) | E17: =IFERROR(-CUMPRINC(Paramètres!B15/12,Paramètres!B16*12,Paramètres!B14,145,156,0),0) | F17: =B17-E17 | G17: =IFERROR(1-F17/Paramètres!B14,0)
A18: 14 | B18: =F17 | C18: =Paramètres!B17*12 | D18: =IFERROR(-CUMIPMT(Paramètres!B15/12,Paramètres!B16*12,Paramètres!B14,157,168,0),0) | E18: =IFERROR(-CUMPRINC(Paramètres!B15/12,Paramètres!B16*12,Paramètres!B14,157,168,0),0) | F18: =B18-E18 | G18: =IFERROR(1-F18/Paramètres!B14,0)
A19: 15 | B19: =F18 | C19: =Paramètres!B17*12 | D19: =IFERROR(-CUMIPMT(Paramètres!B15/12,Paramètres!B16*12,Paramètres!B14,169,180,0),0) | E19: =IFERROR(-CUMPRINC(Paramètres!B15/12,Paramètres!B16*12,Paramètres!B14,169,180,0),0) | F19: =B19-E19 | G19: =IFERROR(1-F19/Paramètres!B14,0)
A20: 16 | B20: =F19 | C20: =Paramètres!B17*12 | D20: =IFERROR(-CUMIPMT(Paramètres!B15/12,Paramètres!B16*12,Paramètres!B14,181,192,0),0) | E20: =IFERROR(-CUMPRINC(Paramètres!B15/12,Paramètres!B16*12,Paramètres!B14,181,192,0),0) | F20: =B20-E20 | G20: =IFERROR(1-F20/Paramètres!B14,0)
A21: 17 | B21: =F20 | C21: =Paramètres!B17*12 | D21: =IFERROR(-CUMIPMT(Paramètres!B15/12,Paramètres!B16*12,Paramètres!B14,193,204,0),0) | E21: =IFERROR(-CUMPRINC(Paramètres!B15/12,Paramètres!B16*12,Paramètres!B14,193,204,0),0) | F21: =B21-E21 | G21: =IFERROR(1-F21/Paramètres!B14,0)
A22: 18 | B22: =F21 | C22: =Paramètres!B17*12 | D22: =IFERROR(-CUMIPMT(Paramètres!B15/12,Paramètres!B16*12,Paramètres!B14,205,216,0),0) | E22: =IFERROR(-CUMPRINC(Paramètres!B15/12,Paramètres!B16*12,Paramètres!B14,205,216,0),0) | F22: =B22-E22 | G22: =IFERROR(1-F22/Paramètres!B14,0)
A23: 19 | B23: =F22 | C23: =Paramètres!B17*12 | D23: =IFERROR(-CUMIPMT(Paramètres!B15/12,Paramètres!B16*12,Paramètres!B14,217,228,0),0) | E23: =IFERROR(-CUMPRINC(Paramètres!B15/12,Paramètres!B16*12,Paramètres!B14,217,228,0),0) | F23: =B23-E23 | G23: =IFERROR(1-F23/Paramètres!B14,0)
A24: 20 | B24: =F23 | C24: =Paramètres!B17*12 | D24: =IFERROR(-CUMIPMT(Paramètres!B15/12,Paramètres!B16*12,Paramètres!B14,229,240,0),0) | E24: =IFERROR(-CUMPRINC(Paramètres!B15/12,Paramètres!B16*12,Paramètres!B14,229,240,0),0) | F24: =B24-E24 | G24: =IFERROR(1-F24/Paramètres!B14,0)
A25: TOTAL | C25: =SUM(C5:C24) | D25: =SUM(D5:D24) | E25: =SUM(E5:E24)

Sheet Revente & Plus-value
A1: SIMULATION DE REVENTE — PLUS-VALUE & FISCALITÉ SCI À L'IS
A2: SCI à l'IS : plus-value imposée à l'IS sur VNC, puis flat tax 30% (PFU) sur dividendes distribués aux associés
A4: HORIZON DE REVENTE
A5: Horizon de revente (années depuis acquisition) | B5: 10 | C5: ans — modifiable
A7: PRIX DE REVENTE ESTIMÉ
A8: Valeur d'acquisition (achat + travaux) | B8: =Paramètres!B5+IFERROR(Paramètres!B8,0)
A9: Taux de revalorisation annuelle (Paramètres!B36) | B9: =Paramètres!B36
A10: Prix de revente estimé | B10: =ROUND((Paramètres!B5+IFERROR(Paramètres!B8,0))*(1+Paramètres!B36)^B5,0)
A12: PLUS-VALUE COMPTABLE (SCI IS)
A13: Amortissements cumulés sur la période | B13: =ROUND(Paramètres!B42*B5,0)
A14: Valeur nette comptable (VNC = Acquisition − Amortissements) | B14: =Paramètres!B5+IFERROR(Paramètres!B8,0)-B13
A15: Plus-value comptable (Prix revente − VNC) | B15: =B10-B14
A17: IMPÔT SUR LES SOCIÉTÉS (IS) SUR LA PLUS-VALUE
A18: IS sur plus-value [15% ≤ 42 500 € — 25% au-delà] | B18: =IF(B15>0,MIN(B15,Paramètres!B39)*Paramètres!B38+MAX(0,B15-Paramètres!B39)*Paramètres!B40,0)
A19: Capital net SCI après IS | B19: =B10-B18
A21: DISTRIBUTION AUX ASSOCIÉS
A22: Capital restant dû à l'horizon (emprunt) | B22: =IFERROR(Paramètres!B14+CUMPRINC(Paramètres!B15/12,Paramètres!B16*12,Paramètres!B14,1,B5*12,0),0)
A23: Disponible après remboursement de l'emprunt | B23: =B19-B22
A24: Flat tax PFU (30%) sur dividendes distribués | B24: =ROUND(MAX(0,B23-Paramètres!B13)*Paramètres!B41,0)
A25: Gain net total (2 associés) | B25: =B23-B24
A26: Gain net par associé (50 % — Lucas Lamquet) | B26: =ROUND((B23-B24)/2,0)
A27: Gain net par associé (50 % — Adrien Fleuriot) | B27: =ROUND((B23-B24)/2,0)
A29: INDICATEUR DE PERFORMANCE
A30: Loyers perçus cumulés sur la période (estimé) | B30: =ROUND(Paramètres!B25*B5,0)
A31: Gain net total (loyers + revente) | B31: =B23-B24+B30
A33: ⚠️ Simulation indicative. L'IS réel dépend des amortissements effectivement constatés, des déficits reportables et de la situation fiscale de la SCI. La flat tax s'applique sur la plus-value de cession de parts ou sur dividendes. Consultez un expert-comptable avant toute décision.
